{
  "ID": 12701,
  "Problem": "Consider the behavior of an integral transform \\\\( \\\\mathcal{L}(f)(s) = \\\\int_0^\\\\infty e^{-st} f(t) \\\\, dt \\\\) known as the Laplace Transform, on a function \\\\( f(t) = e^{At} \\\\), where A is a complex number.\n\nIf given the transformed function \\\\( \\\\mathcal{L}(f)(s) = \\\\frac{1}{s-A} \\\\), can we recover the exact form of \\\\( f(t) \\\\) in the t-domain without any additional information?",
  "Question Type": "from effect to cause without intervention",
  "Ground Truth": "Yes",
  "causal_map": "A → s-A; s-A → 1/(s-A); 1/(s-A) → f(t)",
  "causal_map_integration": "The value of s minus A directly influences the transformed function 1/(s-A), which in turn causally determines the form of f(t) in the t-domain.",
  "Explanation": "The inverse Laplace Transform of \\\\( \\\\frac{1}{s-A} \\\\), under the condition that \\\\( Re(s) > Re(A) \\\\), recovers \\\\( f(t) = e^{At} \\\\). There is a direct correspondence between specific forms of Laplace transformed functions and their originals in the t-domain, enabling exact recovery without further interventions.",
  "zs_prompt": "\nYou are given a problem description and a question. Answer exactly in the JSON format: {\"answer\":\"Yes\"} or {\"answer\":\"No\"}. Do not include any explanations or extra text. \n\nConsider the behavior of an integral transform \\\\( \\\\mathcal{L}(f)(s) = \\\\int_0^\\\\infty e^{-st} f(t) \\\\, dt \\\\) known as the Laplace Transform, on a function \\\\( f(t) = e^{At} \\\\), where A is a complex number.\n\nIf given the transformed function \\\\( \\\\mathcal{L}(f)(s) = \\\\frac{1}{s-A} \\\\), can we recover the exact form of \\\\( f(t) \\\\) in the t-domain without any additional information?",
  "zs_outputs": [
    "{\"answer\":\"Yes\"}",
    "{\"answer\":\"Yes\"}",
    "{\"answer\":\"Yes\"}",
    "{\"answer\":\"Yes\"}",
    "{\"answer\":\"Yes\"}"
  ],
  "zs_answers": [
    "Yes",
    "Yes",
    "Yes",
    "Yes",
    "Yes"
  ],
  "zs_final_ans": "yes",
  "zs_is_acc": true,
  "zs_cot_prompt": "\nYou are given a problem description and a question. Think step by step before answering. After reasoning, output your final answer in the JSON format: {\"answer\":\"Yes\"} or {\"answer\":\"No\"}. \n\nConsider the behavior of an integral transform \\\\( \\\\mathcal{L}(f)(s) = \\\\int_0^\\\\infty e^{-st} f(t) \\\\, dt \\\\) known as the Laplace Transform, on a function \\\\( f(t) = e^{At} \\\\), where A is a complex number.\n\nIf given the transformed function \\\\( \\\\mathcal{L}(f)(s) = \\\\frac{1}{s-A} \\\\), can we recover the exact form of \\\\( f(t) \\\\) in the t-domain without any additional information?",
  "zs_cot_outputs": [
    "Let's reason through this step-by-step:\n\n1. **Understanding the Laplace Transform**: The Laplace transform of a function \\( f(t) \\) is defined as:\n   \\[\n   \\mathcal{L}(f)(s) = \\int_0^\\infty e^{-st} f(t) \\, dt\n   \\]\n   We are given that \\( f(t) = e^{At} \\), where \\( A \\) is a complex number.\n\n2. **Applying the Laplace Transform to \\( f(t) \\)**: \n   \\[\n   \\mathcal{L}(e^{At})(s) = \\int_0^\\infty e^{-st} e^{At} \\, dt = \\int_0^\\infty e^{(A-s)t} \\, dt\n   \\]\n\n3. **Evaluating the Integral**:\n   - For the integral to converge, the real part of \\( s - A \\) must be positive.\n   - Assuming this condition is met, we can evaluate the integral:\n     \\[\n     \\int_0^\\infty e^{(A-s)t} \\, dt = \\left[ \\frac{e^{(A-s)t}}{A-s} \\right]_0^\\infty = \\frac{1}{s-A}\n     \\]\n   This confirms that:\n   \\[\n   \\mathcal{L}(e^{At})(s) = \\frac{1}{s-A}\n   \\]\n\n4. **Recovering \\( f(t) \\) from \\( \\mathcal{L}(f)(s) \\)**:\n   - Given \\( \\mathcal{L}(f)(s) = \\frac{1}{s-A} \\), we know it corresponds to the Laplace transform of \\( e^{At} \\).\n   - The inverse Laplace transform of \\( \\frac{1}{s-A} \\) is indeed \\( e^{At} \\).\n\n5. **Conclusion**:\n   - With the given transformed function \\( \\mathcal{L}(f)(s) = \\frac{1}{s-A} \\), we can uniquely determine that \\( f(t) = e^{At} \\) in the t-domain.\n\nTherefore, the answer is {\"answer\":\"Yes\"}",
    "Let's approach this step-by-step:\n\n1. **Understanding the Problem:**\n   - We are given the Laplace Transform of a function \\( f(t) = e^{At} \\).\n   - The Laplace Transform is given as \\( \\mathcal{L}(f)(s) = \\frac{1}{s-A} \\).\n\n2. **Recall the Definition:**\n   - The Laplace Transform of a function \\( f(t) \\) is defined as:\n     \\[\n     \\mathcal{L}(f)(s) = \\int_0^\\infty e^{-st} f(t) \\, dt\n     \\]\n   - For \\( f(t) = e^{At} \\), we have:\n     \\[\n     \\mathcal{L}(e^{At})(s) = \\int_0^\\infty e^{-st} e^{At} \\, dt = \\int_0^\\infty e^{(A-s)t} \\, dt\n     \\]\n\n3. **Evaluate the Integral:**\n   - To evaluate the integral, we need to consider the condition for convergence.\n   - The integral converges if the real part of \\( s - A \\) is positive, i.e., Re(s) > Re(A).\n   - Assuming this condition is met, we can evaluate the integral:\n     \\[\n     \\int_0^\\infty e^{(A-s)t} \\, dt = \\left[ \\frac{e^{(A-s)t}}{A-s} \\right]_0^\\infty = \\frac{1}{s-A}\n     \\]\n   - This confirms that the Laplace Transform of \\( e^{At} \\) is indeed \\( \\frac{1}{s-A} \\).\n\n4. **Inverse Laplace Transform:**\n   - Given \\( \\mathcal{L}(f)(s) = \\frac{1}{s-A} \\), we need to determine if we can uniquely recover \\( f(t) = e^{At} \\).\n   - The Inverse Laplace Transform states that if \\( \\mathcal{L}(f)(s) = \\frac{1}{s-A} \\), then \\( f(t) = e^{At} \\), provided \\( f(t) \\) is of exponential order and satisfies the conditions for the existence of the Laplace Transform.\n\n5. **Conclusion:**\n   - With the given Laplace Transform and assuming the function \\( f(t) \\) is well-behaved (exponential order and decaying at infinity), we can uniquely recover the original function \\( f(t) = e^{At} \\).\n\nTherefore, the answer is {\"answer\":\"Yes\"}.",
    "Let's reason through this step-by-step:\n\n1. **Understanding the Laplace Transform**: The given Laplace transform is:\n   \\[\n   \\mathcal{L}(f)(s) = \\int_0^\\infty e^{-st} f(t) \\, dt = \\frac{1}{s-A}\n   \\]\n\n2. **Inverse Laplace Transform**: To recover \\( f(t) \\) from its Laplace transform, we need to apply the inverse Laplace transform. The inverse Laplace transform is defined as:\n   \\[\n   f(t) = \\mathcal{L}^{-1}\\left(\\frac{1}{s-A}\\right)\n   \\]\n\n3. **Standard Form of Inverse Laplace Transform**: From tables of Laplace transforms, we know that:\n   \\[\n   \\mathcal{L}^{-1}\\left(\\frac{1}{s-a}\\right) = e^{at}\n   \\]\n   where \\(a\\) is a constant.\n\n4. **Applying the Standard Result**: In our case, the constant \\(a\\) is replaced by \\(A\\):\n   \\[\n   \\mathcal{L}^{-1}\\left(\\frac{1}{s-A}\\right) = e^{At}\n   \\]\n\n5. **Conclusion**: Given the Laplace transform \\(\\frac{1}{s-A}\\), we can directly use the standard result to conclude that the original function \\(f(t)\\) is indeed \\(e^{At}\\).\n\nTherefore, with the given Laplace transform, we can recover the exact form of \\(f(t)\\) in the t-domain without any additional information.\n\n{\"answer\":\"Yes\"}",
    "Let's approach this step-by-step:\n\n1. **Understanding the Problem:**\n   - We have the Laplace transform of a function \\( f(t) \\).\n   - The function is given as \\( f(t) = e^{At} \\), where \\( A \\) is a complex number.\n   - The Laplace transform of \\( f(t) \\) is provided as \\( \\mathcal{L}(f)(s) = \\frac{1}{s-A} \\).\n\n2. **Recall the Inverse Laplace Transform:**\n   - The inverse Laplace transform recovers the original function from its Laplace transform.\n   - For a function \\( F(s) \\), the inverse Laplace transform is denoted as \\( \\mathcal{L}^{-1}(F(s)) \\).\n\n3. **Apply the Inverse Laplace Transform:**\n   - Given \\( \\mathcal{L}(f)(s) = \\frac{1}{s-A} \\), we need to find \\( \\mathcal{L}^{-1}\\left(\\frac{1}{s-A}\\right) \\).\n   - From the properties of the Laplace transform, it is known that:\n     \\[\n     \\mathcal{L}^{-1}\\left(\\frac{1}{s-a}\\right) = e^{at}\n     \\]\n     where \\( a \\) is a constant.\n\n4. **Conclusion:**\n   - Comparing with our given \\( \\mathcal{L}(f)(s) = \\frac{1}{s-A} \\), we see that \\( a = A \\).\n   - Therefore, \\( \\mathcal{L}^{-1}\\left(\\frac{1}{s-A}\\right) = e^{At} \\).\n\n5. **Final Answer:**\n   - We can indeed recover the exact form of \\( f(t) \\) in the t-domain, which is \\( e^{At} \\), using the inverse Laplace transform.\n\nThus, the answer is {\"answer\":\"Yes\"}.",
    "Let's reason through this step-by-step:\n\n1. **Understanding the Laplace Transform**: The Laplace Transform of a function \\( f(t) \\) is defined as:\n   \\[\n   \\mathcal{L}(f)(s) = \\int_0^\\infty e^{-st} f(t) \\, dt\n   \\]\n\n2. **Given Function**: We are given \\( f(t) = e^{At} \\), where \\( A \\) is a complex number.\n\n3. **Transformed Function**: We are also given that the Laplace Transform of \\( f(t) \\) is:\n   \\[\n   \\mathcal{L}(f)(s) = \\frac{1}{s - A}\n   \\]\n\n4. **Inverse Laplace Transform**: The inverse Laplace Transform allows us to recover the original function from its Laplace Transform. For a function \\( F(s) \\), the inverse Laplace Transform is denoted as \\( \\mathcal{L}^{-1}(F(s)) \\).\n\n5. **Recovery of \\( f(t) \\)**: Given \\( \\mathcal{L}(f)(s) = \\frac{1}{s - A} \\), we need to find \\( \\mathcal{L}^{-1}\\left(\\frac{1}{s - A}\\right) \\).\n\n6. **Known Inverse Laplace Transform**: From the properties of the Laplace Transform, we know that:\n   \\[\n   \\mathcal{L}^{-1}\\left(\\frac{1}{s - A}\\right) = e^{At}\n   \\]\n   This is a well-known result for exponential functions.\n\n7. **Conclusion**: Therefore, given the transformed function \\( \\mathcal{L}(f)(s) = \\frac{1}{s - A} \\), we can indeed recover the exact form of \\( f(t) \\) in the t-domain as \\( f(t) = e^{At} \\) without any additional information.\n\nThus, the answer is {\"answer\":\"Yes\"}."
  ],
  "zs_cot_answers": [
    "Yes",
    "Yes",
    "Yes",
    "Yes",
    "Yes"
  ],
  "zs_cot_final_ans": "yes",
  "zs_cot_is_acc": true,
  "zs_causal_prompt": "\nYou are an expert in causal reasoning. Given the following problem description, question, and the causal relationships related to this problem.Answer exactly in the JSON format: {\"answer\":\"Yes\"} or {\"answer\":\"No\"}. Do not include any explanations or extra text. \n\nConsider the behavior of an integral transform \\\\( \\\\mathcal{L}(f)(s) = \\\\int_0^\\\\infty e^{-st} f(t) \\\\, dt \\\\) known as the Laplace Transform, on a function \\\\( f(t) = e^{At} \\\\), where A is a complex number.\n\nIf given the transformed function \\\\( \\\\mathcal{L}(f)(s) = \\\\frac{1}{s-A} \\\\), can we recover the exact form of \\\\( f(t) \\\\) in the t-domain without any additional information?\n\nA → s-A; s-A → 1/(s-A); 1/(s-A) → f(t)",
  "zs_causal_outputs": [
    "{\"answer\":\"Yes\"}",
    "{\"answer\":\"Yes\"}",
    "{\"answer\":\"Yes\"}",
    "{\"answer\":\"Yes\"}",
    "{\"answer\":\"Yes\"}"
  ],
  "zs_causal_answers": [
    "Yes",
    "Yes",
    "Yes",
    "Yes",
    "Yes"
  ],
  "zs_causal_final_ans": "yes",
  "zs_causal_is_acc": true,
  "zs_causal_Inte_prompt": "\nYou are an expert in causal reasoning. Given the following problem description, question, and the causal statements related to this problem.Answer exactly in the JSON format: {\"answer\":\"Yes\"} or {\"answer\":\"No\"}. Do not include any explanations or extra text. \nConsider the behavior of an integral transform \\\\( \\\\mathcal{L}(f)(s) = \\\\int_0^\\\\infty e^{-st} f(t) \\\\, dt \\\\) known as the Laplace Transform, on a function \\\\( f(t) = e^{At} \\\\), where A is a complex number.\n\nIf given the transformed function \\\\( \\\\mathcal{L}(f)(s) = \\\\frac{1}{s-A} \\\\), can we recover the exact form of \\\\( f(t) \\\\) in the t-domain without any additional information?\n\nThe value of s minus A directly influences the transformed function 1/(s-A), which in turn causally determines the form of f(t) in the t-domain.",
  "zs_causal_Inte_outputs": [
    "{\"answer\":\"Yes\"}",
    "{\"answer\":\"Yes\"}",
    "{\"answer\":\"Yes\"}",
    "{\"answer\":\"Yes\"}",
    "{\"answer\":\"Yes\"}"
  ],
  "zs_causal_Inte_answers": [
    "Yes",
    "Yes",
    "Yes",
    "Yes",
    "Yes"
  ],
  "zs_causal_Inte_final_ans": "yes",
  "zs_causal_Inte_is_acc": true,
  "zs_Explanation_prompt": "\nYou are given a problem description, a question, and an explanation. Answer exactly in the JSON format: {\"answer\":\"Yes\"} or {\"answer\":\"No\"}. Do not include any explanations or extra text. \n\nConsider the behavior of an integral transform \\\\( \\\\mathcal{L}(f)(s) = \\\\int_0^\\\\infty e^{-st} f(t) \\\\, dt \\\\) known as the Laplace Transform, on a function \\\\( f(t) = e^{At} \\\\), where A is a complex number.\n\nIf given the transformed function \\\\( \\\\mathcal{L}(f)(s) = \\\\frac{1}{s-A} \\\\), can we recover the exact form of \\\\( f(t) \\\\) in the t-domain without any additional information?\n\nThe inverse Laplace Transform of \\\\( \\\\frac{1}{s-A} \\\\), under the condition that \\\\( Re(s) > Re(A) \\\\), recovers \\\\( f(t) = e^{At} \\\\). There is a direct correspondence between specific forms of Laplace transformed functions and their originals in the t-domain, enabling exact recovery without further interventions.",
  "zs_Explanation_outputs": [
    "{\"answer\":\"Yes\"}",
    "{\"answer\":\"Yes\"}",
    "{\"answer\":\"Yes\"}",
    "{\"answer\":\"Yes\"}",
    "{\"answer\":\"Yes\"}"
  ],
  "zs_Explanation_answers": [
    "Yes",
    "Yes",
    "Yes",
    "Yes",
    "Yes"
  ],
  "zs_Explanation_final_ans": "yes",
  "zs_Explanation_is_acc": true,
  "zs_causal_cot_prompt": "\nYou are an expert in causal reasoning. Given the following problem description, question, and the causal relationships related to this problem.Think step by step before answering. After reasoning, output your final answer in the JSON format: {\"answer\":\"Yes\"} or {\"answer\":\"No\"}. \n\nConsider the behavior of an integral transform \\\\( \\\\mathcal{L}(f)(s) = \\\\int_0^\\\\infty e^{-st} f(t) \\\\, dt \\\\) known as the Laplace Transform, on a function \\\\( f(t) = e^{At} \\\\), where A is a complex number.\n\nIf given the transformed function \\\\( \\\\mathcal{L}(f)(s) = \\\\frac{1}{s-A} \\\\), can we recover the exact form of \\\\( f(t) \\\\) in the t-domain without any additional information?\n\nA → s-A; s-A → 1/(s-A); 1/(s-A) → f(t)",
  "zs_causal_cot_outputs": [
    "To determine if we can recover the exact form of \\( f(t) \\) from the given transformed function, let's reason through the steps:\n\n1. **Given Information**: We have the Laplace transform of \\( f(t) \\):\n   \\[\n   \\mathcal{L}(f)(s) = \\frac{1}{s - A}\n   \\]\n   where \\( A \\) is a complex number.\n\n2. **Inverse Laplace Transform**: The inverse Laplace transform is the operation that recovers the original function \\( f(t) \\) from its Laplace transform \\( \\mathcal{L}(f)(s) \\). For the given transform:\n   \\[\n   \\mathcal{L}(f)(s) = \\frac{1}{s - A}\n   \\]\n\n3. **Inverse Laplace Transform Formula**: The inverse Laplace transform of \\( \\frac{1}{s - A} \\) is known to be:\n   \\[\n   \\mathcal{L}^{-1}\\left(\\frac{1}{s - A}\\right) = e^{At}\n   \\]\n   This result is derived from the standard properties of the Laplace transform.\n\n4. **Verification**: Since the Laplace transform of \\( e^{At} \\) is indeed \\( \\frac{1}{s - A} \\), we can verify that:\n   \\[\n   \\mathcal{L}(e^{At})(s) = \\frac{1}{s - A}\n   \\]\n   Therefore, applying the inverse Laplace transform to \\( \\frac{1}{s - A} \\) should yield \\( e^{At} \\).\n\n5. **Conclusion**: Given the Laplace transform \\( \\mathcal{L}(f)(s) = \\frac{1}{s - A} \\), we can directly use the inverse Laplace transform to recover the exact form of \\( f(t) \\) as \\( e^{At} \\).\n\nThus, we can conclude that the exact form of \\( f(t) \\) can be recovered without any additional information.\n\nOutput:\n```json\n{\"answer\":\"Yes\"}\n```",
    "Let's reason through this step-by-step:\n\n1. We are given the Laplace transform of \\( f(t) = e^{At} \\):\n   \\[\n   \\mathcal{L}(f)(s) = \\int_0^\\infty e^{-st} e^{At} \\, dt = \\int_0^\\infty e^{-(s-A)t} \\, dt = \\frac{1}{s-A}\n   \\]\n   This is valid for \\( \\text{Re}(s) > \\text{Re}(A) \\).\n\n2. The inverse Laplace transform is the process of recovering \\( f(t) \\) from \\( \\mathcal{L}(f)(s) \\). For the given \\( \\mathcal{L}(f)(s) = \\frac{1}{s-A} \\), we know that:\n   \\[\n   \\mathcal{L}^{-1}\\left(\\frac{1}{s-A}\\right) = e^{At}\n   \\]\n   This is true under the condition that \\( \\text{Re}(s) > \\text{Re}(A) \\).\n\n3. The key point here is that the Laplace transform is uniquely defined up to functions that have measure zero in the complex plane. However, without additional information about the domain of \\( t \\) (i.e., whether \\( t \\) is real and non-negative, which is typical for the Laplace transform), we cannot definitively state that \\( f(t) = e^{At} \\) is the only possible function.\n\n4. If we assume \\( t \\) is real and non-negative, then the function \\( f(t) = e^{At} \\) is indeed the unique solution to the given Laplace transform.\n\nGiven this reasoning, we can conclude that with the information provided, we can recover the exact form of \\( f(t) \\) in the t-domain, assuming \\( t \\) is real and non-negative.\n\n{\"answer\":\"Yes\"}",
    "Let's break down the problem step by step:\n\n1. **Given Information**:\n   - The Laplace transform of \\( f(t) = e^{At} \\) is \\( \\mathcal{L}(f)(s) = \\frac{1}{s-A} \\).\n   - We need to determine if we can recover the exact form of \\( f(t) \\) from the transformed function \\( \\mathcal{L}(f)(s) \\).\n\n2. **Understanding the Laplace Transform**:\n   - The Laplace transform of \\( e^{At} \\) for \\( t \\geq 0 \\) is indeed \\( \\frac{1}{s-A} \\). This is a well-known property of the Laplace transform.\n\n3. **Reversing the Laplace Transform**:\n   - To recover \\( f(t) \\) from \\( \\mathcal{L}(f)(s) \\), we need to apply the inverse Laplace transform.\n   - The inverse Laplace transform of \\( \\frac{1}{s-A} \\) is \\( e^{At} \\) for \\( t \\geq 0 \\).\n\n4. **Causal Relationship Analysis**:\n   - The relationship between the input \\( f(t) = e^{At} \\) and its Laplace transform \\( \\mathcal{L}(f)(s) = \\frac{1}{s-A} \\) is one-to-one within the context of the Laplace transform for functions that are zero for negative \\( t \\) (causal systems).\n   - Given \\( \\mathcal{L}(f)(s) = \\frac{1}{s-A} \\), the only function in the time domain that satisfies this is \\( f(t) = e^{At} \\).\n\n5. **Conclusion**:\n   - With the given transformed function \\( \\mathcal{L}(f)(s) = \\frac{1}{s-A} \\), we can uniquely recover \\( f(t) = e^{At} \\) without any additional information.\n\nTherefore, the answer is:\n\n```json\n{\"answer\":\"Yes\"}\n```",
    "To determine if we can recover the exact form of \\( f(t) \\) in the t-domain from the given Laplace transform \\( \\mathcal{L}(f)(s) = \\frac{1}{s-A} \\), let's reason through this step by step:\n\n1. **Given Information**: We have the Laplace transform of \\( f(t) \\) as \\( \\mathcal{L}(f)(s) = \\frac{1}{s-A} \\).\n\n2. **Inverse Laplace Transform**: The inverse Laplace transform is a well-defined operation that maps a function in the s-domain back to the t-domain. Specifically, for a function \\( F(s) \\) in the s-domain, its inverse Laplace transform \\( f(t) \\) is given by:\n   \\[\n   f(t) = \\mathcal{L}^{-1}\\left\\{\\frac{1}{s-A}\\right\\}\n   \\]\n\n3. **Standard Inverse Laplace Transform**: It is a standard result in Laplace transform theory that:\n   \\[\n   \\mathcal{L}^{-1}\\left\\{\\frac{1}{s-a}\\right\\} = e^{at}\n   \\]\n   where \\( a \\) is a constant (in our case, \\( a = A \\)).\n\n4. **Application to Given Problem**: Applying the above standard result to our specific case:\n   \\[\n   \\mathcal{L}^{-1}\\left\\{\\frac{1}{s-A}\\right\\} = e^{At}\n   \\]\n\n5. **Conclusion**: Therefore, the exact form of \\( f(t) \\) in the t-domain is \\( e^{At} \\), which matches the form provided in the problem statement.\n\nBased on this reasoning, we can conclude that yes, the exact form of \\( f(t) \\) can be recovered from the given Laplace transform without any additional information.\n\n```json\n{\"answer\":\"Yes\"}\n```",
    "Let's reason through this step-by-step:\n\n1. **Given Information**:\n   - We have the Laplace transform of \\( f(t) = e^{At} \\): \\( \\mathcal{L}(f)(s) = \\frac{1}{s-A} \\).\n   - We need to determine if we can recover \\( f(t) \\) exactly from this information.\n\n2. **Understanding the Laplace Transform**:\n   - The Laplace transform of \\( f(t) = e^{At} \\) is indeed \\( \\mathcal{L}(f)(s) = \\frac{1}{s-A} \\).\n   - This is a well-known property of the Laplace transform for exponential functions.\n\n3. **Reversing the Laplace Transform**:\n   - To find \\( f(t) \\) from \\( \\mathcal{L}(f)(s) = \\frac{1}{s-A} \\), we need to use the inverse Laplace transform.\n   - The inverse Laplace transform of \\( \\frac{1}{s-A} \\) is \\( e^{At} \\).\n\n4. **Verification**:\n   - We know that applying the Laplace transform to \\( e^{At} \\) gives us \\( \\frac{1}{s-A} \\).\n   - Applying the inverse Laplace transform to \\( \\frac{1}{s-A} \\) should give us back \\( e^{At} \\).\n\n5. **Conclusion**:\n   - Since the Laplace transform and its inverse are bijective (one-to-one and onto) in the appropriate domain, we can uniquely recover \\( f(t) = e^{At} \\) from \\( \\mathcal{L}(f)(s) = \\frac{1}{s-A} \\).\n\nTherefore, the answer is:\n\n{\"answer\":\"Yes\"}"
  ],
  "zs_causal_cot_answers": [
    "Yes",
    "Yes",
    "Yes",
    "Yes",
    "Yes"
  ],
  "zs_causal_cot_final_ans": "yes",
  "zs_causal_cot_is_acc": true
}