{
  "ID": 3571,
  "Problem": "Consider a complex-valued function \\\\( z(t) = e^{iAt}w \\\\) where \\\\( A \\\\) is a real constant and \\\\( w \\\\) is a complex constant vector. We analyze the effect of applying a Fourier transform \\\\( \\\\mathcal{F} \\\\) to this function over time \\\\( t \\\\).\n\nIf at a certain time \\\\( t_1 \\\\), a modulation by \\\\( e^{iCt} \\\\) (where \\\\( C \\\\) is another real constant) is applied to \\\\( z(t) \\\\) as an intervention, will the transformed function \\\\( \\\\mathcal{F}\\\\{z(t)\\\\}(\\\\omega) \\\\) for \\\\( \\\\omega \\\\) be independent of \\\\( C \\\\)?",
  "Question Type": "from cause to effect with intervention",
  "Ground Truth": "no",
  "Explanation": "The intervention introduces an additional frequency component to \\\\( z(t) \\\\) reflected in its transform. The resulting Fourier transform will have contributions from both \\\\( A \\\\) and \\\\( C \\\\), manifesting as additional frequency components or shifts, thus making it dependent on \\\\( C \\\\) as well as \\\\( A \\\\).",
  "causal_map": "e^(iAt) → z(t); w → z(t); z(t) → F{z(t)}(ω); e^(iCt) → modulation_of_z(t); modulation_of_z(t) → F{modulation_of_z(t)}(ω); F{z(t)}(ω) ← F{modulation_of_z(t)}(ω)",
  "causal_map_integration": "A → z(t); w → z(t); z(t) → F{z(t)}(ω); e^(iCt) → modulation_of_z(t); modulation_of_z(t) → F{modulation_of_z(t)}(ω); F{z(t)}(ω) ← F{modulation_of_z(t)}(ω)",
  "zs_outputs": [
    "{\"answer\":\"No\"}",
    "{\"answer\":\"No\"}",
    "{\"answer\":\"No\"}",
    "{\"answer\":\"No\"}",
    "{\"answer\":\"No\"}"
  ],
  "zs_answers": [
    "No",
    "No",
    "No",
    "No",
    "No"
  ],
  "zs_final_ans": "no",
  "zs_is_acc": true,
  "zs_cot_outputs": [
    "Let's break down the problem step by step.\n\n1. **Initial Function**: The original function is \\( z(t) = e^{iAt}w \\), where \\( A \\) is a real constant, and \\( w \\) is a complex constant vector.\n\n2. **Fourier Transform of Initial Function**: The Fourier transform of \\( z(t) \\) is:\n   \\[\n   \\mathcal{F}\\{z(t)\\}(\\omega) = \\int_{-\\infty}^{\\infty} e^{iAt} w \\cdot e^{-i\\omega t} dt\n   \\]\n   This can be simplified to:\n   \\[\n   \\mathcal{F}\\{z(t)\\}(\\omega) = w \\int_{-\\infty}^{\\infty} e^{i(A-\\omega)t} dt\n   \\]\n   The integral evaluates to a Dirac delta function:\n   \\[\n   \\mathcal{F}\\{z(t)\\}(\\omega) = 2\\pi w \\delta(\\omega - A)\n   \\]\n\n3. **Intervention with Modulation**: At time \\( t_1 \\), a modulation by \\( e^{iCt} \\) is applied to \\( z(t) \\). This means the new function becomes:\n   \\[\n   z'(t) = e^{iAt}w \\cdot e^{iC(t-t_1)} = e^{iA(t-t_1)}e^{iC(t-t_1)}w = e^{i(A+C)(t-t_1)}w\n   \\]\n\n4. **Fourier Transform of Modulated Function**: The Fourier transform of the modulated function \\( z'(t) \\) is:\n   \\[\n   \\mathcal{F}\\{z'(t)\\}(\\omega) = \\int_{-\\infty}^{\\infty} e^{i(A+C)(t-t_1)} w \\cdot e^{-i\\omega t} dt\n   \\]\n   Simplifying the exponent:\n   \\[\n   \\mathcal{F}\\{z'(t)\\}(\\omega) = w \\int_{-\\infty}^{\\infty} e^{i(A+C)(t-t_1)} e^{-i\\omega t} dt\n   \\]\n   Let \\( u = t - t_1 \\), then:\n   \\[\n   \\mathcal{F}\\{z'(t)\\}(\\omega) = w \\int_{-\\infty}^{\\infty} e^{i(A+C)u} e^{-i\\omega(u+t_1)} du\n   \\]\n   This simplifies to:\n   \\[\n   \\mathcal{F}\\{z'(t)\\}(\\omega) = w e^{-i\\omega t_1} \\int_{-\\infty}^{\\infty} e^{i(A+C-u\\omega)} du\n   \\]\n   The integral again evaluates to a Dirac delta function:\n   \\[\n   \\mathcal{F}\\{z'(t)\\}(\\omega) = 2\\pi w e^{-i\\omega t_1} \\delta(\\omega - (A+C))\n   \\]\n\n5. **Conclusion**: The transformed function after the modulation is:\n   \\[\n   \\mathcal{F}\\{z'(t)\\}(\\omega) = 2\\pi w e^{-i\\omega t_1} \\delta(\\omega - (A+C))\n   \\]\n   The term \\( e^{-i\\omega t_1} \\) is dependent on \\( t_1 \\), but not on \\( C \\) directly in the context of the delta function argument. However, the presence of \\( C \\) in the argument of the delta function indicates that the transformed function is indeed affected by \\( C \\).\n\nTherefore, the transformed function \\( \\mathcal{F}\\{z(t)\\}(\\omega) \\) for \\( \\omega \\) is not independent of \\( C \\).\n\n```json\n{\"answer\":\"No\"}\n```",
    "Let's approach this step-by-step:\n\n1. **Original Function**: The original function is \\( z(t) = e^{iAt}w \\).\n\n2. **Fourier Transform of Original Function**: The Fourier transform of \\( z(t) \\) is:\n   \\[\n   \\mathcal{F}\\{z(t)\\}(\\omega) = \\int_{-\\infty}^{\\infty} e^{iAt}w \\cdot e^{-i\\omega t} dt = w \\int_{-\\infty}^{\\infty} e^{i(A-\\omega)t} dt\n   \\]\n   This integral is a Dirac delta function:\n   \\[\n   \\mathcal{F}\\{z(t)\\}(\\omega) = 2\\pi w \\delta(\\omega - A)\n   \\]\n\n3. **Intervention**: At time \\( t_1 \\), a modulation by \\( e^{iCt} \\) is applied to \\( z(t) \\). So the new function becomes:\n   \\[\n   z'(t) = e^{iAt}w \\cdot e^{iC(t-t_1)} = e^{iA(t-t_1)}e^{iC(t-t_1)}w = e^{i(A+C)(t-t_1)}w\n   \\]\n\n4. **Fourier Transform of Modulated Function**: The Fourier transform of \\( z'(t) \\) is:\n   \\[\n   \\mathcal{F}\\{z'(t)\\}(\\omega) = \\int_{-\\infty}^{\\infty} e^{i(A+C)(t-t_1)}w \\cdot e^{-i\\omega t} dt = w e^{-i\\omega t_1} \\int_{-\\infty}^{\\infty} e^{i(A+C-\\omega)t} dt\n   \\]\n   Again, this integral is a Dirac delta function:\n   \\[\n   \\mathcal{F}\\{z'(t)\\}(\\omega) = 2\\pi w e^{-i\\omega t_1} \\delta(\\omega - (A+C))\n   \\]\n\n5. **Comparison**: Comparing the Fourier transforms:\n   - Original: \\( 2\\pi w \\delta(\\omega - A) \\)\n   - Modulated: \\( 2\\pi w e^{-i\\omega t_1} \\delta(\\omega - (A+C)) \\)\n\n   We see that the Fourier transform changes due to the modulation, specifically the term \\( e^{-i\\omega t_1} \\) and the shift in the delta function from \\( A \\) to \\( A+C \\).\n\n6. **Conclusion**: The transformed function \\( \\mathcal{F}\\{z(t)\\}(\\omega) \\) is not independent of \\( C \\) because the presence of \\( C \\) shifts the frequency content of the signal.\n\nTherefore, the answer is {\"answer\":\"No\"}.",
    "Let's approach this step-by-step:\n\n1. **Initial Function**: \n   The initial function is \\( z(t) = e^{iAt}w \\), where \\( A \\) is a real constant and \\( w \\) is a complex constant vector.\n\n2. **Fourier Transform**:\n   The Fourier transform of \\( z(t) \\) is given by:\n   \\[\n   \\mathcal{F}\\{z(t)\\}(\\omega) = \\int_{-\\infty}^{\\infty} e^{iAt}w \\cdot e^{-i\\omega t} dt\n   \\]\n   This can be simplified to:\n   \\[\n   \\mathcal{F}\\{z(t)\\}(\\omega) = w \\int_{-\\infty}^{\\infty} e^{i(A - \\omega)t} dt\n   \\]\n   This integral converges only if \\( A = \\omega \\), and then it evaluates to a Dirac delta function:\n   \\[\n   \\mathcal{F}\\{z(t)\\}(\\omega) = 2\\pi w \\delta(\\omega - A)\n   \\]\n\n3. **Modulation Intervened**:\n   If we apply a modulation by \\( e^{iCt} \\) at time \\( t_1 \\), the new function becomes:\n   \\[\n   z'(t) = \\begin{cases}\n   e^{iAt}w & \\text{for } t < t_1 \\\\\n   e^{iAt}e^{iC(t-t_1)}w & \\text{for } t \\geq t_1\n   \\end{cases}\n   \\]\n   This can be written as:\n   \\[\n   z'(t) = e^{iAt}w + e^{iC(t-t_1)}e^{iAt}w - e^{iAt}w = e^{iAt}w(1 + e^{iC(t-t_1)} - 1) = e^{iAt}w e^{iC(t-t_1)}\n   \\]\n   Simplifying further:\n   \\[\n   z'(t) = e^{i(A+C)(t-t_1)}e^{iAt}w\n   \\]\n\n4. **Fourier Transform of Modulated Function**:\n   The Fourier transform of \\( z'(t) \\) is:\n   \\[\n   \\mathcal{F}\\{z'(t)\\}(\\omega) = \\int_{-\\infty}^{\\infty} e^{i(A+C)(t-t_1)}e^{iAt}w e^{-i\\omega t} dt\n   \\]\n   Simplifying inside the integral:\n   \\[\n   \\mathcal{F}\\{z'(t)\\}(\\omega) = e^{-iA\\omega t_1} w \\int_{-\\infty}^{\\infty} e^{i(A+C - \\omega)t} dt\n   \\]\n   This again simplifies to:\n   \\[\n   \\mathcal{F}\\{z'(t)\\}(\\omega) = 2\\pi e^{-iA\\omega t_1} w \\delta(\\omega - (A+C))\n   \\]\n\n5. **Independence of \\( C \\)**:\n   From the above result, we see that the Fourier transform after the modulation depends on \\( C \\) through the term \\( e^{-iA\\omega t_1} \\). This term clearly shows that the transformed function is not independent of \\( C \\).\n\nTherefore, the answer is {\"answer\":\"No\"}.",
    "Let's break down the problem step-by-step:\n\n1. **Original Function**: The original function is \\( z(t) = e^{iAt}w \\), where \\( A \\) is a real constant and \\( w \\) is a complex constant vector.\n\n2. **Modulation**: At time \\( t_1 \\), a modulation by \\( e^{iCt} \\) is applied. This means the function becomes \\( z(t) = e^{iAt}w \\cdot e^{iC(t-t_1)} \\) for \\( t \\geq t_1 \\). For simplicity, let's consider the function after the modulation has been applied, which can be written as:\n   \\[\n   z'(t) = \\begin{cases} \n   e^{iAt}w & \\text{if } t < t_1 \\\\\n   e^{iAt}w \\cdot e^{iC(t-t_1)} & \\text{if } t \\geq t_1 \n   \\end{cases}\n   \\]\n\n3. **Fourier Transform**: The Fourier transform of a function \\( f(t) \\) is defined as:\n   \\[\n   \\mathcal{F}\\{f(t)\\}(\\omega) = \\int_{-\\infty}^{\\infty} f(t) e^{-i\\omega t} dt\n   \\]\n   Applying the Fourier transform to \\( z(t) \\) gives us:\n   \\[\n   \\mathcal{F}\\{z(t)\\}(\\omega) = \\int_{-\\infty}^{\\infty} e^{iAt}w e^{-i\\omega t} dt\n   \\]\n   Simplifying the exponent:\n   \\[\n   \\mathcal{F}\\{z(t)\\}(\\omega) = w \\int_{-\\infty}^{\\infty} e^{i(A-\\omega)t} dt\n   \\]\n   This integral is a Dirac delta function:\n   \\[\n   \\mathcal{F}\\{z(t)\\}(\\omega) = 2\\pi w \\delta(A - \\omega)\n   \\]\n\n4. **Effect of Modulation**: After the modulation, the Fourier transform of \\( z'(t) \\) will change due to the additional phase factor \\( e^{iC(t-t_1)} \\). However, since the Fourier transform is linear and the modulation happens at a specific time, the overall effect on the Fourier transform can be analyzed as follows:\n   \\[\n   \\mathcal{F}\\{z'(t)\\}(\\omega) = \\int_{-\\infty}^{\\infty} z'(t) e^{-i\\omega t} dt\n   \\]\n   Splitting the integral into two parts (before and after \\( t_1 \\)):\n   \\[\n   \\mathcal{F}\\{z'(t)\\}(\\omega) = \\int_{-\\infty}^{t_1} e^{iAt}w e^{-i\\omega t} dt + \\int_{t_1}^{\\infty} e^{iAt}w \\cdot e^{iC(t-t_1)} e^{-i\\omega t} dt\n   \\]\n   Simplifying the exponents in each part:\n   \\[\n   \\mathcal{F}\\{z'(t)\\}(\\omega) = w \\left( \\int_{-\\infty}^{t_1} e^{i(A-\\omega)t} dt + \\int_{t_1}^{\\infty} e^{i(A+\\Re(C)-\\omega)t} dt \\right)\n   \\]\n   Both integrals are again Dirac delta functions, but with different arguments:\n   \\[\n   \\mathcal{F}\\{z'(t)\\}(\\omega) = 2\\pi w \\left( \\delta(A - \\omega) + \\delta((A+\\Re(C)) - \\omega) \\right)\n   \\]\n\n5. **Independence from \\( C \\)**: The transformed function \\( \\mathcal{F}\\{z'(t)\\}(\\omega) \\) includes both \\( \\delta(A - \\omega) \\) and \\( \\delta((A+\\Re(C)) - \\omega) \\). Therefore, the transformed function depends on \\( C \\) through the term \\( \\delta((A+\\Re(C)) - \\omega) \\).\n\n**Conclusion**: The transformed function \\( \\mathcal{F}\\{z(t)\\}(\\omega) \\) is not independent of \\( C \\).\n\n```json\n{\"answer\":\"No\"}\n```",
    "Let's approach this step-by-step:\n\n1. **Original Function**: The original function is \\( z(t) = e^{iAt}w \\), where \\( A \\) is a real constant and \\( w \\) is a complex constant vector.\n\n2. **Fourier Transform of Original Function**:\n   - The Fourier transform of \\( z(t) \\) is given by:\n     \\[\n     \\mathcal{F}\\{z(t)\\}(\\omega) = \\int_{-\\infty}^{\\infty} e^{iAt}w \\cdot e^{-i\\omega t} dt\n     \\]\n   - Simplifying, we get:\n     \\[\n     \\mathcal{F}\\{z(t)\\}(\\omega) = w \\int_{-\\infty}^{\\infty} e^{i(A-\\omega)t} dt\n     \\]\n   - This integral converges if \\( A \\neq \\omega \\). For \\( A \\neq \\omega \\), the result is:\n     \\[\n     \\mathcal{F}\\{z(t)\\}(\\omega) = 2\\pi w \\delta(\\omega - A)\n     \\]\n     where \\( \\delta \\) is the Dirac delta function.\n\n3. **Modulation by \\( e^{iCt} \\)**:\n   - Applying the modulation, the new function becomes:\n     \\[\n     z'(t) = e^{iAt}w \\cdot e^{iCt} = e^{i(A+C)t}w\n     \\]\n\n4. **Fourier Transform of Modulated Function**:\n   - The Fourier transform of \\( z'(t) \\) is:\n     \\[\n     \\mathcal{F}\\{z'(t)\\}(\\omega) = \\int_{-\\infty}^{\\infty} e^{i(A+C)t}w \\cdot e^{-i\\omega t} dt\n     \\]\n   - Simplifying, we get:\n     \\[\n     \\mathcal{F}\\{z'(t)\\}(\\omega) = w \\int_{-\\infty}^{\\infty} e^{i((A+C)-\\omega)t} dt\n     \\]\n   - For \\( A + C \\neq \\omega \\), this results in:\n     \\[\n     \\mathcal{F}\\{z'(t)\\}(\\omega) = 2\\pi w \\delta(\\omega - (A+C))\n     \\]\n\n5. **Comparison**:\n   - The Fourier transform after modulation depends on \\( A + C \\).\n   - Specifically, it is \\( 2\\pi w \\delta(\\omega - (A+C)) \\), which clearly depends on \\( C \\).\n\n6. **Conclusion**:\n   - The transformed function \\( \\mathcal{F}\\{z(t)\\}(\\omega) \\) is not independent of \\( C \\) because the argument of the Dirac delta function changes from \\( A \\) to \\( A + C \\).\n\nTherefore, the answer is {\"answer\":\"No\"}."
  ],
  "zs_cot_answers": [
    "No",
    "No",
    "No",
    "No",
    "No"
  ],
  "zs_cot_final_ans": "no",
  "zs_cot_is_acc": true,
  "zs_Explanation_outputs": [
    "{\"answer\":\"No\"}",
    "{\"answer\":\"No\"}",
    "{\"answer\":\"No\"}",
    "{\"answer\":\"No\"}",
    "{\"answer\":\"No\"}"
  ],
  "zs_Explanation_answers": [
    "No",
    "No",
    "No",
    "No",
    "No"
  ],
  "zs_Explanation_final_ans": "no",
  "zs_Explanation_is_acc": true,
  "zs_causal_outputs": [
    "{\"answer\":\"No\"}",
    "{\"answer\":\"No\"}",
    "{\"answer\":\"No\"}",
    "{\"answer\":\"No\"}",
    "{\"answer\":\"No\"}"
  ],
  "zs_causal_answers": [
    "No",
    "No",
    "No",
    "No",
    "No"
  ],
  "zs_causal_final_ans": "no",
  "zs_causal_is_acc": true,
  "zs_causal_Inte_outputs": [
    "{\"answer\":\"No\"}",
    "{\"answer\":\"No\"}",
    "{\"answer\":\"No\"}",
    "{\"answer\":\"No\"}",
    "{\"answer\":\"No\"}"
  ],
  "zs_causal_Inte_answers": [
    "No",
    "No",
    "No",
    "No",
    "No"
  ],
  "zs_causal_Inte_final_ans": "no",
  "zs_causal_Inte_is_acc": true,
  "zs_causal_cot_prompt": "\nYou are an expert in causal reasoning. Given the following problem description, question, and the causal relationships related to this problem.Think step by step before answering. After reasoning, output your final answer in the JSON format: {\"answer\":\"Yes\"} or {\"answer\":\"No\"}. \n\nConsider a complex-valued function \\\\( z(t) = e^{iAt}w \\\\) where \\\\( A \\\\) is a real constant and \\\\( w \\\\) is a complex constant vector. We analyze the effect of applying a Fourier transform \\\\( \\\\mathcal{F} \\\\) to this function over time \\\\( t \\\\).\n\nIf at a certain time \\\\( t_1 \\\\), a modulation by \\\\( e^{iCt} \\\\) (where \\\\( C \\\\) is another real constant) is applied to \\\\( z(t) \\\\) as an intervention, will the transformed function \\\\( \\\\mathcal{F}\\\\{z(t)\\\\}(\\\\omega) \\\\) for \\\\( \\\\omega \\\\) be independent of \\\\( C \\\\)?\n\ne^(iAt) → z(t); w → z(t); z(t) → F{z(t)}(ω); e^(iCt) → modulation_of_z(t); modulation_of_z(t) → F{modulation_of_z(t)}(ω); F{z(t)}(ω) ← F{modulation_of_z(t)}(ω)",
  "zs_causal_cot_outputs": [
    "Let's reason through this step by step.\n\n1. **Initial Function**: The original function is \\( z(t) = e^{iAt}w \\).\n\n2. **Fourier Transform of \\( z(t) \\)**: The Fourier transform of \\( z(t) \\) is given by:\n   \\[\n   \\mathcal{F}\\{z(t)\\}(\\omega) = \\int_{-\\infty}^{\\infty} e^{iAt}w \\cdot e^{-i\\omega t} dt = w \\int_{-\\infty}^{\\infty} e^{i(At - \\omega t)} dt = w \\int_{-\\infty}^{\\infty} e^{i(A - \\omega)t} dt\n   \\]\n   This integral is the Fourier transform of a complex exponential, which results in a Dirac delta function:\n   \\[\n   \\mathcal{F}\\{z(t)\\}(\\omega) = w \\cdot 2\\pi \\delta(\\omega - A)\n   \\]\n\n3. **Modulation by \\( e^{iCt} \\)**: Applying the modulation \\( e^{iCt} \\) to \\( z(t) \\) gives:\n   \\[\n   \\text{modulation\\_of\\_z}(t) = e^{iCt} \\cdot e^{iAt}w = e^{i(C+A)t}w\n   \\]\n\n4. **Fourier Transform of Modulated Function**: The Fourier transform of the modulated function is:\n   \\[\n   \\mathcal{F}\\{\\text{modulation\\_of\\_z}(t)\\}(\\omega) = \\int_{-\\infty}^{\\infty} e^{i(C+A)t}w \\cdot e^{-i\\omega t} dt = w \\int_{-\\infty}^{\\infty} e^{i((C+A) - \\omega)t} dt\n   \\]\n   Again, this is a Fourier transform of a complex exponential, resulting in a Dirac delta function:\n   \\[\n   \\mathcal{F}\\{\\text{modulation\\_of\\_z}(t)\\}(\\omega) = w \\cdot 2\\pi \\delta(\\omega - (C + A))\n   \\]\n\n5. **Comparison**: Comparing the two Fourier transforms:\n   - Original: \\( \\mathcal{F}\\{z(t)\\}(\\omega) = w \\cdot 2\\pi \\delta(\\omega - A) \\)\n   - Modulated: \\( \\mathcal{F}\\{\\text{modulation\\_of\\_z}(t)\\}(\\omega) = w \\cdot 2\\pi \\delta(\\omega - (C + A)) \\)\n\nThe transformed function after modulation depends on the value of \\( C \\). Therefore, the transformed function \\( \\mathcal{F}\\{z(t)\\}(\\omega) \\) is not independent of \\( C \\).\n\n{\"answer\":\"No\"}",
    "Let's break down the problem step by step:\n\n1. **Original Function**: The original function is \\( z(t) = e^{iAt}w \\), where \\( A \\) is a real constant and \\( w \\) is a complex constant vector.\n\n2. **Fourier Transform of Original Function**: Applying the Fourier transform \\( \\mathcal{F} \\) to \\( z(t) \\):\n   \\[\n   \\mathcal{F}\\{z(t)\\}(\\omega) = \\mathcal{F}\\{e^{iAt}w\\}(\\omega)\n   \\]\n   Using the property of the Fourier transform that \\( \\mathcal{F}\\{e^{iAt}f(t)\\}(\\omega) = 2\\pi f(-A + \\omega) \\) for a constant \\( A \\), we get:\n   \\[\n   \\mathcal{F}\\{z(t)\\}(\\omega) = 2\\pi w e^{-iA\\omega}\n   \\]\n\n3. **Modulation by \\( e^{iCt} \\)**: Now, apply a modulation by \\( e^{iCt} \\) to \\( z(t) \\):\n   \\[\n   \\text{modulation\\_of\\_z}(t) = e^{iCt}z(t) = e^{iCt}e^{iAt}w = e^{i(C+A)t}w\n   \\]\n\n4. **Fourier Transform of Modulated Function**: Apply the Fourier transform to the modulated function:\n   \\[\n   \\mathcal{F}\\{\\text{modulation\\_of\\_z}(t)\\}(\\omega) = \\mathcal{F}\\{e^{i(C+A)t}w\\}(\\omega)\n   \\]\n   Again, using the same Fourier transform property:\n   \\[\n   \\mathcal{F}\\{\\text{modulation\\_of\\_z}(t)\\}(\\omega) = 2\\pi w e^{-i(C+A)\\omega}\n   \\]\n\n5. **Comparison**: Compare the Fourier transforms:\n   - For the original function: \\( \\mathcal{F}\\{z(t)\\}(\\omega) = 2\\pi w e^{-iA\\omega} \\)\n   - For the modulated function: \\( \\mathcal{F}\\{\\text{modulation\\_of\\_z}(t)\\}(\\omega) = 2\\pi w e^{-i(C+A)\\omega} \\)\n\n   Notice that the Fourier transform of the modulated function includes an additional phase factor \\( e^{-iC\\omega} \\) compared to the original function.\n\n6. **Independence from \\( C \\)**: The transformed function \\( \\mathcal{F}\\{\\text{modulation\\_of\\_z}(t)\\}(\\omega) \\) does depend on \\( C \\) because it introduces a phase shift that is dependent on \\( C \\).\n\nTherefore, the transformed function \\( \\mathcal{F}\\{z(t)\\}(\\omega) \\) is not independent of \\( C \\).\n\n```json\n{\"answer\":\"No\"}\n```",
    "Let's break down the problem step by step.\n\n1. **Original Function**: The original function is \\( z(t) = e^{iAt}w \\), where \\( A \\) is a real constant and \\( w \\) is a complex constant vector.\n\n2. **Fourier Transform of Original Function**: The Fourier transform of \\( z(t) \\) is given by:\n   \\[\n   \\mathcal{F}\\{z(t)\\}(\\omega) = \\int_{-\\infty}^{\\infty} e^{iAt}w \\cdot e^{-i\\omega t} dt = w \\int_{-\\infty}^{\\infty} e^{i(A - \\omega)t} dt.\n   \\]\n   This integral converges if \\( A \\neq \\omega \\), and the result is:\n   \\[\n   \\mathcal{F}\\{z(t)\\}(\\omega) = 2\\pi w \\delta(\\omega - A),\n   \\]\n   where \\( \\delta \\) is the Dirac delta function.\n\n3. **Modulation by \\( e^{iCt} \\)**: If we apply a modulation by \\( e^{iCt} \\) to \\( z(t) \\), the new function becomes:\n   \\[\n   z'(t) = e^{iCt} z(t) = e^{iCt} e^{iAt} w = e^{i(C+A)t} w.\n   \\]\n\n4. **Fourier Transform of Modulated Function**: The Fourier transform of \\( z'(t) \\) is:\n   \\[\n   \\mathcal{F}\\{z'(t)\\}(\\omega) = \\int_{-\\infty}^{\\infty} e^{i(C+A)t} w \\cdot e^{-i\\omega t} dt = w \\int_{-\\infty}^{\\infty} e^{i((C+A) - \\omega)t} dt.\n   \\]\n   This integral also converges if \\( C + A \\neq \\omega \\), and the result is:\n   \\[\n   \\mathcal{F}\\{z'(t)\\}(\\omega) = 2\\pi w \\delta(\\omega - (A+C)).\n   \\]\n\n5. **Comparison**: The Fourier transform of the modulated function \\( \\mathcal{F}\\{z'(t)\\}(\\omega) \\) is:\n   \\[\n   \\mathcal{F}\\{z'(t)\\}(\\omega) = 2\\pi w \\delta(\\omega - (A+C)),\n   \\]\n   which clearly depends on \\( C \\).\n\nTherefore, the transformed function \\( \\mathcal{F}\\{z(t)\\}(\\omega) \\) for \\( \\omega \\) is not independent of \\( C \\).\n\n```json\n{\"answer\":\"No\"}\n```",
    "Let's break down the problem step-by-step:\n\n1. **Initial Function**: The original function is \\( z(t) = e^{iAt}w \\), where \\( A \\) is a real constant, and \\( w \\) is a complex constant vector.\n\n2. **Fourier Transform of Initial Function**: The Fourier transform of \\( z(t) \\) is given by:\n   \\[\n   \\mathcal{F}\\{z(t)\\}(\\omega) = \\int_{-\\infty}^{\\infty} e^{iAt}w \\cdot e^{-i\\omega t} dt = w \\int_{-\\infty}^{\\infty} e^{i(A - \\omega)t} dt\n   \\]\n   This integral converges if \\( A \\neq \\omega \\). If \\( A = \\omega \\), the integral diverges. For simplicity, let's assume \\( A \\neq \\omega \\).\n\n3. **Modulation**: At time \\( t_1 \\), a modulation by \\( e^{iCt} \\) is applied to \\( z(t) \\). The new function becomes:\n   \\[\n   z'(t) = e^{iAt}w \\cdot e^{iCt} = e^{i(A + C)t}w\n   \\]\n\n4. **Fourier Transform of Modulated Function**: The Fourier transform of the modulated function \\( z'(t) \\) is:\n   \\[\n   \\mathcal{F}\\{z'(t)\\}(\\omega) = \\int_{-\\infty}^{\\infty} e^{i(A + C)t}w \\cdot e^{-i\\omega t} dt = w \\int_{-\\infty}^{\\infty} e^{i((A + C) - \\omega)t} dt\n   \\]\n   Again, assuming \\( A + C \\neq \\omega \\), this integral converges.\n\n5. **Comparison**: Comparing the Fourier transforms of the initial and modulated functions, we see that:\n   \\[\n   \\mathcal{F}\\{z(t)\\}(\\omega) = w \\int_{-\\infty}^{\\infty} e^{i(A - \\omega)t} dt\n   \\]\n   \\[\n   \\mathcal{F}\\{z'(t)\\}(\\omega) = w \\int_{-\\infty}^{\\infty} e^{i((A + C) - \\omega)t} dt\n   \\]\n   These integrals are different because they have different exponents inside the integrals, specifically \\( A - \\omega \\) vs. \\( (A + C) - \\omega \\).\n\n6. **Conclusion**: The Fourier transform of the modulated function \\( \\mathcal{F}\\{z'(t)\\}(\\omega) \\) is not independent of \\( C \\).\n\nTherefore, the answer is {\"answer\":\"No\"}.",
    "Let's reason through this step-by-step:\n\n1. **Initial Function**: The original function is \\( z(t) = e^{iAt}w \\).\n\n2. **Modulation**: At time \\( t_1 \\), we apply a modulation \\( e^{iCt} \\) to \\( z(t) \\). This means the new function becomes:\n   \\[\n   z_{\\text{mod}}(t) = e^{iCt} \\cdot e^{iAt}w = e^{i(C+A)t}w\n   \\]\n\n3. **Fourier Transform of the Original Function**: The Fourier transform of \\( z(t) \\) is:\n   \\[\n   \\mathcal{F}\\{z(t)\\}(\\omega) = \\int_{-\\infty}^{\\infty} e^{iAt}w \\cdot e^{-i\\omega t} dt = w \\cdot \\mathcal{F}\\{e^{iAt}\\}(\\omega)\n   \\]\n   The Fourier transform of \\( e^{iAt} \\) is:\n   \\[\n   \\mathcal{F}\\{e^{iAt}\\}(\\omega) = 2\\pi \\delta(\\omega - A)\n   \\]\n   So,\n   \\[\n   \\mathcal{F}\\{z(t)\\}(\\omega) = 2\\pi w \\delta(\\omega - A)\n   \\]\n\n4. **Fourier Transform of the Modulated Function**: Now, let's find the Fourier transform of \\( z_{\\text{mod}}(t) \\):\n   \\[\n   \\mathcal{F}\\{z_{\\text{mod}}(t)\\}(\\omega) = \\int_{-\\infty}^{\\infty} e^{i(C+A)t}w \\cdot e^{-i\\omega t} dt = w \\cdot \\mathcal{F}\\{e^{i(C+A)t}\\}(\\omega)\n   \\]\n   The Fourier transform of \\( e^{i(C+A)t} \\) is:\n   \\[\n   \\mathcal{F}\\{e^{i(C+A)t}\\}(\\omega) = 2\\pi \\delta(\\omega - (C+A))\n   \\]\n   So,\n   \\[\n   \\mathcal{F}\\{z_{\\text{mod}}(t)\\}(\\omega) = 2\\pi w \\delta(\\omega - (C+A))\n   \\]\n\n5. **Comparison**: Comparing the Fourier transforms:\n   - For the original function: \\( \\mathcal{F}\\{z(t)\\}(\\omega) = 2\\pi w \\delta(\\omega - A) \\)\n   - For the modulated function: \\( \\mathcal{F}\\{z_{\\text{mod}}(t)\\}(\\omega) = 2\\pi w \\delta(\\omega - (C+A)) \\)\n\n   The Fourier transform of the modulated function depends on \\( C \\), as it shifts the delta function by \\( C \\).\n\nTherefore, the transformed function \\( \\mathcal{F}\\{z(t)\\}(\\omega) \\) is not independent of \\( C \\).\n\nOutput: {\"answer\": \"No\"}"
  ],
  "zs_causal_cot_answers": [
    "No",
    "No",
    "No",
    "No",
    "No"
  ],
  "zs_causal_cot_final_ans": "no",
  "zs_causal_cot_is_acc": true
}